MANIFEST.in
README.md
setup.py
MRedis.egg-info/PKG-INFO
MRedis.egg-info/SOURCES.txt
MRedis.egg-info/dependency_links.txt
MRedis.egg-info/requires.txt
MRedis.egg-info/top_level.txt
mredis/__init__.py
mredis/badge.py
mredis/channel.py
mredis/containers.py
mredis/counter.py
mredis/database.py
mredis/exception.py
mredis/lock.py
mredis/rate_limit.py
mredis/tests/__init__.py
mredis/tests/test_basic.py
mredis/tests/test_channel.py
mredis/tests/test_containers.py
mredis/tests/test_counter.py
mredis/tests/test_func.py