Metadata-Version: 1.1
Name: MRedis
Version: 0.2
Summary: redis wrapper
Home-page: https://github.com/GeorgeWang1994/MRedis
Author: georgewang
Author-email: georgewang1994@163.com
License: MIT
Keywords: redis client python
Platform: UNKNOWN
Classifier: Development Status :: 5 - Production/Stable
Classifier: Intended Audience :: Developers
Classifier: License :: OSI Approved :: MIT License
Classifier: Operating System :: OS Independent
Classifier: Programming Language :: Python
Classifier: Programming Language :: Python :: 2
Classifier: Programming Language :: Python :: 2.7
Classifier: Programming Language :: Python :: 3
Classifier: Programming Language :: Python :: 3.4
Classifier: Programming Language :: Python :: 3.5
Classifier: Programming Language :: Python :: 3.6
